apollonai/__init__.py
apollonai/core.py
apollonai/main.py
apollonai/utils.py
apollonai/core/__init__.py
apollonai/modules/__init__.py
apollonai/modules/path/__init__.py
apollonai/modules/path/path_manager.py
apollonai/modules/pipeline/__init__.py
apollonai/modules/pipeline/pipeline_manager.py
apollonai/modules/pipeline/types/__init__.py
apollonai/modules/pipeline/types/step_type.py
apollonai-0.1.3.dist-info/METADATA
apollonai-0.1.3.dist-info/WHEEL
apollonai-0.1.3.dist-info/entry_points.txt
apollonai-0.1.3.dist-info/top_level.txt
apollonai-0.1.3.dist-info/RECORD
