Metadata-Version: 2.1
Name: apollonai
Version: 0.1.3
Summary: CyberAiBot AI Library
Home-page: https://github.com/CYBA7K2M-DATAPROJ/DATAPROJ_ai_library.git
Author: Antoine Fusilier
Author-email: antoinefusilier@gmail.com
License: MIT
Classifier: Programming Language :: Python :: 3
Classifier: License :: OSI Approved :: MIT License
Classifier: Operating System :: OS Independent
Requires-Python: >=3.6
Requires-Dist: typer
Requires-Dist: util4all
